aletk/ResultMonad.py
aletk/__init__.py
aletk/_version.py
aletk/adapters.py
aletk/py.typed
aletk/utils.py
aletk-0.1.6.dist-info/LICENSE
aletk-0.1.6.dist-info/METADATA
aletk-0.1.6.dist-info/WHEEL
aletk-0.1.6.dist-info/top_level.txt
aletk-0.1.6.dist-info/RECORD
