Metadata-Version: 2.2
Name: aletk
Version: 0.1.6
Summary: Collection of general purpose tools to work with Python
Author-email: Luis Alejandro Bordo García <bgluiszz@gmail.com>
License: MIT
Project-URL: Repository, https://gitlab.com/alebg/aletk
Classifier: Programming Language :: Python :: 3
Classifier: Programming Language :: Python :: 3.13
Classifier: License :: OSI Approved :: MIT License
Classifier: Operating System :: OS Independent
Classifier: Intended Audience :: Developers
Classifier: Typing :: Typed
Requires-Python: >=3.13
License-File: LICENSE
Requires-Dist: fuzzywuzzy
Requires-Dist: python-Levenshtein
Provides-Extra: dev
Requires-Dist: mypy; extra == "dev"
Requires-Dist: black; extra == "dev"
Requires-Dist: pytest; extra == "dev"
Requires-Dist: jupyter; extra == "dev"
